test/__init__.py
test/conftest.py
test/test_buffer.py
test/test_cli.py
test/test_dotenv.py
test/test_errors.py
test/test_export.py
test/test_foreach.py
test/test_functions.py
test/test_globals.py
test/test_import.py
test/test_interpreter.py
test/test_load.py
test/test_raw.py
test/test_sql.py
test/low_level/test_YAML_comments.py
test/low_level/test_buffer.py
test/low_level/test_dotenv.py
test/low_level/test_export_YAML.py
test/low_level/test_stack.py
test/low_level/test_to_functions.py
test/source/import1.yaml
test/source/module1.py
test/source/test1.yaml
test/source/test2.yaml
test/source/test_function.yaml
test/source/test_module.yaml
yamlpp/__init__.py
yamlpp/buffer.py
yamlpp/cli.py
yamlpp/core.py
yamlpp/dotenv.py
yamlpp/error.py
yamlpp/import_modules.py
yamlpp/sql.py
yamlpp/stack.py
yamlpp/util.py
yamlpp/yamlpp_schema.yaml
yamlpp_lang-0.3.3.dist-info/licenses/LICENSE
yamlpp_lang-0.3.3.dist-info/METADATA
yamlpp_lang-0.3.3.dist-info/WHEEL
yamlpp_lang-0.3.3.dist-info/entry_points.txt
yamlpp_lang-0.3.3.dist-info/top_level.txt
yamlpp_lang-0.3.3.dist-info/RECORD
